polymerization_planner/__init__.py
polymerization_planner/main.py
polymerization_planner/test_runner.py
polymerization_planner/atrp/__init__.py
polymerization_planner/atrp/calculator.py
polymerization_planner/pet_raft/__init__.py
polymerization_planner/pet_raft/calculator.py
polymerization_planner-0.1.3.dist-info/licenses/LICENSE
polymerization_planner-0.1.3.dist-info/METADATA
polymerization_planner-0.1.3.dist-info/WHEEL
polymerization_planner-0.1.3.dist-info/entry_points.txt
polymerization_planner-0.1.3.dist-info/top_level.txt
polymerization_planner-0.1.3.dist-info/RECORD
