Metadata-Version: 2.4
Name: polymerization_planner
Version: 0.1.3
Summary: A tool to generate polymerization reaction recipes from user-defined molar ratios and stock concentrations. Please see the PDF instruction in the GitHub link provided.
Home-page: https://github.com/C3344/polymerization_planner/blob/main/polymerization_planner/docs/tutorial.pdf
Author: Cesar Ramirez
Author-email: cr828@scarletmail.rutgers.edu
Classifier: Programming Language :: Python :: 3
Classifier: License :: OSI Approved :: MIT License
Classifier: Operating System :: OS Independent
Requires-Python: >=3.7
License-File: LICENSE
Requires-Dist: pandas
Requires-Dist: openpyxl
Requires-Dist: numpy
Dynamic: author
Dynamic: author-email
Dynamic: classifier
Dynamic: description
Dynamic: description-content-type
Dynamic: home-page
Dynamic: license-file
Dynamic: requires-dist
Dynamic: requires-python
Dynamic: summary
